asymetry/__init__.py
asymetry/api/__init__.py
asymetry/api/client.py
asymetry/config.py
asymetry/exporter.py
asymetry/instrumentation.py
asymetry/main.py
asymetry/openai_agents.py
asymetry/spans.py
asymetry/token_utils.py
asymetry/tracing.py
asymetry/version.py
asymetry-0.1.6.dist-info/METADATA
asymetry-0.1.6.dist-info/WHEEL
asymetry-0.1.6.dist-info/RECORD
