Metadata-Version: 2.4
Name: asymetry
Version: 0.1.6
Summary: LLM observability SDK for OpenAI and Anthropic
License: MIT
Keywords: llm,observability,openai,monitoring,tracing,anthropic
Author: Asymetry Team
Requires-Python: >=3.10,<4.0
Classifier: Development Status :: 3 - Alpha
Classifier: Intended Audience :: Developers
Classifier: License :: OSI Approved :: MIT License
Classifier: Programming Language :: Python :: 3
Classifier: Programming Language :: Python :: 3.10
Classifier: Programming Language :: Python :: 3.11
Classifier: Programming Language :: Python :: 3.12
Classifier: Programming Language :: Python :: 3.13
Classifier: Programming Language :: Python :: 3.14
Provides-Extra: agents
Requires-Dist: anthropic (==0.72.0)
Requires-Dist: httpx (>=0.27.0,<0.28.0)
Requires-Dist: openai (>=1.0.0,<2.0.0)
Requires-Dist: openai-agents (>=0.0.16,<0.0.17) ; extra == "agents"
Requires-Dist: opentelemetry-api (==1.20.0)
Requires-Dist: opentelemetry-sdk (==1.20.0)
Requires-Dist: python-dotenv (>=1.0.0,<2.0.0)
Requires-Dist: tiktoken (>=0.8.0,<0.9.0)
Project-URL: Documentation, https://docs.asymetry.co
Project-URL: Homepage, https://asymetry.co
Project-URL: Repository, https://github.com/asymetry/asymetry-sdk
